payx_cli/__init__.py
payx_cli/commands/__init__.py
payx_cli/commands/main.py
payx_cli/models/__init__.py
payx_cli/services/__init__.py
payx_cli/utils/__init__.py
payx_cli-0.1.0.dist-info/METADATA
payx_cli-0.1.0.dist-info/WHEEL
payx_cli-0.1.0.dist-info/RECORD
