Metadata-Version: 2.3
Name: payx-cli
Version: 0.1.0
Summary: A CLI tool for automating engineer onboarding tasks including processor setup, test transactions, merchant migration, and environment configuration management.
License: MIT
Author: Rakibul Haq
Author-email: haq.rakibul@gmail.com
Requires-Python: >=3.13
Classifier: License :: OSI Approved :: MIT License
Classifier: Programming Language :: Python :: 3
Classifier: Programming Language :: Python :: 3.13
Requires-Dist: typer (>=0.21.0,<0.22.0)
